pymodaq_plugins_basler/__init__.py
pymodaq_plugins_basler/utils.py
pymodaq_plugins_basler/app/__init__.py
pymodaq_plugins_basler/daq_move_plugins/__init__.py
pymodaq_plugins_basler/daq_viewer_plugins/__init__.py
pymodaq_plugins_basler/daq_viewer_plugins/plugins_0D/__init__.py
pymodaq_plugins_basler/daq_viewer_plugins/plugins_1D/__init__.py
pymodaq_plugins_basler/daq_viewer_plugins/plugins_2D/__init__.py
pymodaq_plugins_basler/daq_viewer_plugins/plugins_2D/daq_2Dviewer_Basler.py
pymodaq_plugins_basler/daq_viewer_plugins/plugins_ND/__init__.py
pymodaq_plugins_basler/exporters/__init__.py
pymodaq_plugins_basler/extensions/__init__.py
pymodaq_plugins_basler/hardware/__init__.py
pymodaq_plugins_basler/hardware/basler.py
pymodaq_plugins_basler/models/__init__.py
pymodaq_plugins_basler/resources/__init__.py
pymodaq_plugins_basler/resources/config_acA1920-40gm.json
pymodaq_plugins_basler/resources/config_puA1600-60um.json
pymodaq_plugins_basler/resources/config_template.toml
pymodaq_plugins_basler/resources/extended_publisher.py
pymodaq_plugins_basler/scanners/__init__.py
pymodaq_plugins_basler-5.1.0.dist-info/METADATA
pymodaq_plugins_basler-5.1.0.dist-info/WHEEL
pymodaq_plugins_basler-5.1.0.dist-info/entry_points.txt
pymodaq_plugins_basler-5.1.0.dist-info/licenses/LICENSE
pymodaq_plugins_basler-5.1.0.dist-info/RECORD
