Metadata-Version: 2.4
Name: pymodaq_plugins_basler
Version: 5.1.0
Summary: PyMoDAQ plugins for cameras of Basler
Project-URL: Homepage, https://pymodaq.cnrs.fr
Project-URL: Documentation , https://pymodaq.cnrs.fr
Project-URL: Repository , https://github.com/PyMoDAQ/pymodaq_plugins_basler
Author-email: Benedikt Burger <Benedikt.Burger@physik.tu-darmstadt.de>, Romain GeneauX <romain.geneaux@cea.fr>
Maintainer-email: Romain GeneauX <romain.geneaux@cea.fr>
License: The MIT License (MIT)
License-File: LICENSE
Classifier: Development Status :: 5 - Production/Stable
Classifier: Intended Audience :: Science/Research
Classifier: License :: OSI Approved :: MIT License
Classifier: Natural Language :: English
Classifier: Operating System :: OS Independent
Classifier: Programming Language :: Python :: 3.8
Classifier: Programming Language :: Python :: 3.9
Classifier: Programming Language :: Python :: 3.10
Classifier: Programming Language :: Python :: 3.11
Classifier: Topic :: Scientific/Engineering :: Human Machine Interfaces
Classifier: Topic :: Scientific/Engineering :: Visualization
Classifier: Topic :: Software Development :: Libraries :: Python Modules
Classifier: Topic :: Software Development :: User Interfaces
Requires-Python: >=3.9
Requires-Dist: h5py
Requires-Dist: imageio
Requires-Dist: numpy
Requires-Dist: pymodaq>=4.4.7
Requires-Dist: pypylon
Requires-Dist: pywin32; sys_platform == 'win32'
Requires-Dist: uuid6
